Workbook

Sheet Sales
A1: Order ID | B1: Order date | C1: Country | D1: Product ID | E1: Customer | F1: Quantity | G1: Unit price | H1: Amount | I1: Sales rep | J1: Status
A2: O1001 | B2: 46023 | C2: France | D2: P101 | E2: Alice Martin | F2: 1 | G2: 2.5 | H2: 2.5 | I2: Maya | J2: Returned
A3: O1002 | B3: 46061 | C3: Israel | D3: P106 | E3: Ben Cohen | F3: 8 | G3: 2.9 | H3: 23.2 | I3: Noah | J3: Completed
A4: O1003 | B4: 46096 | C4: Germany | D4: P103 | E4: Clara Levy | F4: 3 | G4: 2.2 | H4: 6.6 | I4: Lia | J4: Completed
A5: O1004 | B5: 46134 | C5: Spain | D5: P108 | E5: David Klein | F5: 10 | G5: 5.2 | H5: 52 | I5: Maya | J5: Completed
A6: O1005 | B6: 46144 | C6: France | D6: P105 | E6: Alice Martin | F6: 5 | G6: 1.6 | H6: 8 | I6: Noah | J6: Completed
A7: O1006 | B7: 46182 | C7: Israel | D7: P102 | E7: Ben Cohen | F7: 12 | G7: 1.8 | H7: 21.6 | I7: Lia | J7: Completed
A8: O1007 | B8: 46038 | C8: Germany | D8: P107 | E8: Clara Levy | F8: 7 | G8: 2.1 | H8: 14.7 | I8: Maya | J8: Completed
A9: O1008 | B9: 46076 | C9: Spain | D9: P104 | E9: David Klein | F9: 2 | G9: 4.5 | H9: 9 | I9: Noah | J9: Completed
A10: O1009 | B10: 46084 | C10: France | D10: P102 | E10: Alice Martin | F10: 9 | G10: 1.8 | H10: 16.2 | I10: Lia | J10: Completed
A11: O1010 | B11: 46122 | C11: Germany | D11: P107 | E11: Ben Cohen | F11: 4 | G11: 2.1 | H11: 8.4 | I11: Maya | J11: Completed
A12: O1011 | B12: 46159 | C12: Spain | D12: P104 | E12: Clara Levy | F12: 11 | G12: 4.5 | H12: 49.5 | I12: Noah | J12: Completed
A13: O1012 | B13: 46197 | C13: France | D13: P101 | E13: David Klein | F13: 6 | G13: 2.5 | H13: 15 | I13: Lia | J13: Returned
... A65: O1064 | B65: 46122 | C65: Germany | D65: P103 | E65: David Klein | F65: 10 | G65: 2.2 | H65: 22 | I65: Maya | J65: Completed

Sheet Products
A1: Product ID | B1: Product | C1: Category | D1: Unit price
A2: P101 | B2: Apple | C2: Fruit | D2: 2.5
A3: P102 | B3: Banana | C3: Fruit | D3: 1.8
A4: P103 | B4: Orange | C4: Fruit | D4: 2.2
A5: P104 | B5: Mango | C5: Fruit | D5: 4.5
A6: P105 | B6: Carrot | C6: Vegetable | D6: 1.6
A7: P106 | B7: Tomato | C7: Vegetable | D7: 2.9
A8: P107 | B8: Cucumber | C8: Vegetable | D8: 2.1
A9: P108 | B9: Avocado | C9: Fruit | D9: 5.2

Sheet Practice
A1: EXERCISES — enter formulas in the blank cells
A2: Weighted scores | B2: Score | C2: Weight | D2: Result
A3: Test 1 | B3: 85 | C3: 0.2
A4: Test 2 | B4: 90 | C4: 0.3
A5: Test 3 | B5: 75 | C5: 0.5
A6: Weighted total | D6: =SUMPRODUCT(B3:B5,C3:C5) -> 81.5
A12: IF / AND / OR | B12: Quantity | C12: Amount | D12: Decision
A13: Order A | B13: 12 | C13: 62.4 | D13: =IF(OR(B13>=10, C13>=50),"Priority","Standard") -> Priority | E13: =NOT(C13>10) -> FALSE | F13: 100
A14: Order B | B14: 3 | C14: 5.4 | D14: =IF(OR(B14>=10, C14>=50),"Priority","Standard") -> Standard
A15: Order C | B15: 9 | C15: 26.1 | D15: =IF(OR(B15>=10, C15>=50),"Priority","Standard") -> Standard
A17: Cleaning practice | B17: Raw customer | D17: Cleaned text | G17: Combined text
A18: C01 | B18: Alice Martin | C18: =RIGHT(A18,2) -> 01 | D18: =TRIM(CLEAN(B18)) -> Alice Martin | G18: France | H18: Paris
A19: C02 | B19: Ben Cohen | C19: =MID(A19,2,2) -> 02 | D19: =TRIM(CLEAN(B19)) -> Ben Cohen | G19: Israel | H19: Tel Aviv
A20: C03 | B20: Clara Levy | C20: =RIGHT(A20,2) -> 03 | D20: =TRIM(CLEAN(B20)) -> Clara Levy | G20: Germany | H20: Berlin
A21: C04 | B21: David Klein | C21: =RIGHT(A21,2) -> 04 | D21: =TRIM(CLEAN(B21)) -> David Klein | G21: Espagne | H21: Madrid
D22: =TRIM(CLEAN(B22)) | G22: Espagne | H22: Madrid
A24: What-if practice | B24: Value
A25: Units sold | B25: 100
A26: Price per unit | B26: 12
A27: Variable cost per unit | B27: 5
A28: Fixed costs | B28: 250
A29: Profit — enter formula | B29: =(B25*B26)-(B25*B27)-B28 -> 450

Sheet Lookups
A1: LOOKUPS — VLOOKUP → HLOOKUP → INDEX + MATCH
A3: 1. VLOOKUP (vertical) | B3: Product ID | C3: Product name | D3: Category
A4: Find details for | B4: P104 | C4: =VLOOKUP(B4,Products!A2:D9,2,FALSE) -> Mango | D4: =VLOOKUP(B4,Products!A2:D9,3,FALSE) -> Fruit
A5: Find details for | B5: P107 | C5: =VLOOKUP(B5,Products!A3:D10,2,FALSE) -> Cucumber | D5: =VLOOKUP(B5,Products!A3:D10,3,FALSE) -> Vegetable
A8: 2. HLOOKUP (horizontal)
A9: Product ID | B9: P101 | C9: P104 | D9: P107 | E9: P108
A10: Product | B10: Apple | C10: Mango | D10: Cucumber | E10: Avocado
A11: Category | B11: Fruit | C11: Fruit | D11: Vegetable | E11: Fruit
A12: Unit price | B12: 2.5 | C12: 4.5 | D12: 2.1 | E12: 5.2
A14: Find details for | B14: Product ID | C14: Product name | D14: Category
A15: Look up in row 9 | B15: P104 | C15: =HLOOKUP(B15,$A$9:$E$12,2,FALSE) -> Mango | D15: =HLOOKUP(B15,$A$9:$E$12,3,FALSE) -> Fruit
A16: Look up in row 9 | B16: P107 | C16: =HLOOKUP(B16,$A$9:$E$12,2,FALSE) -> Cucumber | D16: =HLOOKUP(B16,$A$9:$E$12,3,FALSE) -> Vegetable
A19: 3. INDEX + MATCH | B19: Product ID | C19: Product name | D19: Category
A20: Find details for | B20: P104 | C20: =INDEX(Products!B2:B9,MATCH(B20,Products!A2:A9,0)) -> Mango | D20: =INDEX(Products!C2:C9,MATCH(C20,Products!B2:B9,0)) -> Fruit
A21: Find details for | B21: P107 | C21: =INDEX(Products!B3:B10,MATCH(B21,Products!A3:A10,0)) -> Cucumber | D21: =INDEX(Products!C3:C10,MATCH(C21,Products!B3:B10,0)) -> Vegetable
A23: Use Products for sections 1 and 3; use the horizontal table above for section 2.
